test/__init__.py
test/test_env_vars_data.py
wellsrt_data_client/__init__.py
wellsrt_data_client/common.py
wellsrt_data_client/commons/__init__.py
wellsrt_data_client/commons/dev_utils.py
wellsrt_data_client/commons/env_variables.py
wellsrt_data_client/commons/key_vaults.py
wellsrt_data_client/commons/utils.py
wellsrt_data_client/services/__init__.py
wellsrt_data_client/services/adx/__init__.py
wellsrt_data_client/services/adx/az_adx_data_service.py
wellsrt_data_client/services/caches/__init__.py
wellsrt_data_client/services/caches/keys/__init__.py
wellsrt_data_client/services/caches/keys/dataset_key_info.py
wellsrt_data_client/services/caches/keys/key_info.py
wellsrt_data_client/services/caches/keys/sys_settings_key.py
wellsrt_data_client/services/cores/__init__.py
wellsrt_data_client/services/cores/az_ad_authz_service.py
wellsrt_data_client/services/cores/az_storage_account_service.py
wellsrt_data_client/services/cores/send_email_service.py
wellsrt_data_client/services/cosmos/__init__.py
wellsrt_data_client/services/cosmos/az_cosmos_data_service.py
wellsrt_data_client/services/snow/__init__.py
wellsrt_data_client/services/snow/snow_data_service.py
wellsrt_data_client/services/wellsrt/__init__.py
wellsrt_data_client/services/wellsrt/wellsrt_cbt_data_service.py
wellsrt_data_client/services/wellsrt/wellsrt_metadata_service.py
wellsrt_data_client/services/wellsrt/wits_data_service.py
wellsrt_data_client/services/wellsrt/wits_metadata_service.py
wellsrt_data_client-0.0.6.dist-info/METADATA
wellsrt_data_client-0.0.6.dist-info/WHEEL
wellsrt_data_client-0.0.6.dist-info/top_level.txt
wellsrt_data_client-0.0.6.dist-info/RECORD
